config_types/__init__.py
config_types/pydantic.py
config_types-0.2.2.dist-info/licenses/LICENSE.txt
config_types-0.2.2.dist-info/WHEEL
config_types-0.2.2.dist-info/METADATA
config_types-0.2.2.dist-info/RECORD
