Metadata-Version: 2.4
Name: config-types
Version: 0.2.2
Summary: Types for use with environment imported configurations
Keywords: 12-factor,configuration,typing,validation
Author: Melvyn Sopacua
Author-email: Melvyn Sopacua <2403540-melvyn-sopacua@users.noreply.gitlab.com>
License-Expression: BSD-2-Clause
License-File: LICENSE.txt
Classifier: Development Status :: 3 - Alpha
Classifier: Framework :: Pydantic :: 2
Classifier: Intended Audience :: Developers
Classifier: Intended Audience :: System Administrators
Classifier: License :: OSI Approved :: BSD License
Classifier: Programming Language :: Python :: 3.10
Classifier: Programming Language :: Python :: 3.11
Classifier: Programming Language :: Python :: 3.12
Classifier: Programming Language :: Python :: 3.13
Classifier: Topic :: Internet :: WWW/HTTP :: Site Management
Requires-Dist: pydantic-settings>=2.11.0 ; extra == 'pydantic'
Requires-Python: >=3.12
Provides-Extra: pydantic
